{
  "subject_id": "OAS1_0004_MR1",
  "slice_index": 64,
  "source_file": "data\\raw\\OAS1_0004_MR1\\RAW\\OAS1_0004_MR1_mpr-1_anon.img",
  "generated_at": "2026-06-17T06:29:54.873623Z",
  "pipeline_version": "0.1.0",
  "modality": "T1-weighted",
  "plane": "sagittal",
  "image_quality": "good",
  "anatomy": {
    "visible_structures": [
      "cerebral cortex",
      "cerebellum",
      "brainstem",
      "corpus callosum",
      "cerebral aqueduct",
      "fourth ventricle"
    ],
    "hemisphere_symmetry": "not applicable \u2014 sagittal view",
    "cortical_ribbon": "preserved",
    "sulcal_pattern": "normal depth"
  },
  "tissue_findings": {
    "gray_matter": "Appears normal in signal intensity and morphology.",
    "white_matter": "Appears normal in signal intensity and morphology.",
    "ventricles": "The lateral ventricles and third ventricle are normal in size and shape. The cerebral aqueduct and fourth ventricle are patent.",
    "sulci_gyri": "The sulci and gyri are well-defined and appear normal in depth.",
    "basal_ganglia": "Not clearly delineated in this sagittal slice.",
    "thalamus": "Appears normal in signal intensity and morphology.",
    "cerebellum": "Appears normal in signal intensity and morphology.",
    "brainstem": "Appears normal in signal intensity and morphology."
  },
  "pathology_flags": {
    "atrophy": false,
    "atrophy_severity": "none",
    "white_matter_lesions": false,
    "lesion_count_estimate": "none",
    "mass_effect": false,
    "midline_shift": false,
    "hydrocephalus": false,
    "infarct": false,
    "hemorrhage": false,
    "notes": "No acute intracranial abnormalities are identified."
  },
  "global_impression": "This sagittal T1-weighted image demonstrates normal anatomy of the brain, cerebellum, and brainstem. There is no evidence of atrophy, white matter lesions, mass effect, or hemorrhage.",
  "confidence": 1.0,
  "oasis_metadata": {
    "age": 28,
    "sex": "M",
    "handedness": "R",
    "education_years": null,
    "mmse": null,
    "cdr": null,
    "nwbv": 0.803,
    "etiv": "1588",
    "asf": 1.105
  },
  "validation": {
    "passed": true,
    "issues": []
  }
}